kastle/__init__.py
kastle/kastle.py
kastle-0.0.1.dist-info/LICENSE
kastle-0.0.1.dist-info/METADATA
kastle-0.0.1.dist-info/WHEEL
kastle-0.0.1.dist-info/top_level.txt
kastle-0.0.1.dist-info/RECORD
