Metadata-Version: 2.1
Name: kastle
Version: 0.0.1
Summary: KASTLE
Home-page: https://github.com/I-E-E-E/KAML
Author: Will Wang
Author-email: No.1@pku.edu.cn
Classifier: Programming Language :: Python :: 3
Classifier: License :: OSI Approved :: MIT License
Classifier: Operating System :: OS Independent
Requires-Python: >=3.6
License-File: LICENSE
